mkdocs_caption/__init__.py
mkdocs_caption/_version.py
mkdocs_caption/config.py
mkdocs_caption/custom.py
mkdocs_caption/helper.py
mkdocs_caption/image.py
mkdocs_caption/logger.py
mkdocs_caption/plugin.py
mkdocs_caption/post_processor.py
mkdocs_caption/table.py
mkdocs_caption-1.3.0.dist-info/METADATA
mkdocs_caption-1.3.0.dist-info/WHEEL
mkdocs_caption-1.3.0.dist-info/entry_points.txt
mkdocs_caption-1.3.0.dist-info/licenses/LICENSE
mkdocs_caption-1.3.0.dist-info/RECORD
