Metadata-Version: 2.4
Name: mkdocs-caption
Version: 1.3.0
Summary: Enhance your MkDocs documentation with easy figure, table captioning and numbering.
Project-URL: Documentation, https://github.com/tobiasah/mkdocs-caption#readme
Project-URL: Issues, https://github.com/tobiasah/mkdocs-caption/issues
Project-URL: Source, https://github.com/tobiasah/mkdocs-caption
Author-email: Tobias Ahrens <tobias.ahrens@posteo.de>
License-Expression: MIT
License-File: LICENSE
Classifier: Development Status :: 4 - Beta
Classifier: Programming Language :: Python
Classifier: Programming Language :: Python :: 3.8
Classifier: Programming Language :: Python :: 3.9
Classifier: Programming Language :: Python :: 3.10
Classifier: Programming Language :: Python :: 3.11
Classifier: Programming Language :: Python :: 3.12
Classifier: Programming Language :: Python :: 3.13
Classifier: Programming Language :: Python :: Implementation :: CPython
Classifier: Programming Language :: Python :: Implementation :: PyPy
Requires-Python: >=3.8
Requires-Dist: lxml
Requires-Dist: mkdocs
